django_ensuresuperuser/__init__.py
django_ensuresuperuser/apps.py
django_ensuresuperuser/management/__init__.py
django_ensuresuperuser/management/commands/__init__.py
django_ensuresuperuser/management/commands/ensuresuperuser.py
django_ensuresuperuser-0.1.1.dist-info/licenses/LICENSE
django_ensuresuperuser-0.1.1.dist-info/METADATA
django_ensuresuperuser-0.1.1.dist-info/WHEEL
django_ensuresuperuser-0.1.1.dist-info/top_level.txt
django_ensuresuperuser-0.1.1.dist-info/RECORD
