Metadata-Version: 2.4
Name: django-ensuresuperuser
Version: 0.1.1
Summary: Create a superuser if it doesn't exist, in the non interactive mode, using environment variables to set the email and password
Requires-Python: >=3.10
License-File: LICENSE
Requires-Dist: django>=4.2
Dynamic: license-file
